{
  "db_name": "SQLite",
  "query": "select *\nfrom tiny_auth_password_pbkdf2hmacsha256\nwhere password = ?1\n",
  "describe": {
    "columns": [
      {
        "name": "id",
        "ordinal": 0,
        "type_info": "Integer"
      },
      {
        "name": "password",
        "ordinal": 1,
        "type_info": "Integer"
      },
      {
        "name": "credential",
        "ordinal": 2,
        "type_info": "Blob"
      },
      {
        "name": "iterations",
        "ordinal": 3,
        "type_info": "Integer"
      },
      {
        "name": "salt",
        "ordinal": 4,
        "type_info": "Blob"
      }
    ],
    "parameters": {
      "Right": 1
    },
    "nullable": [
      false,
      false,
      false,
      false,
      false
    ]
  },
  "hash": "255a48834194aaee5f32350787639d07905d99841efc066387f158e18931cfcc"
}
